hdtools/__init__.py
hdtools/address.py
hdtools/bech32.py
hdtools/conversions.py
hdtools/crypto_utils.py
hdtools/extended_keys.py
hdtools/keys.py
hdtools/message.py
hdtools/network.py
hdtools/nt_utils.py
hdtools/opcodes.py
hdtools/script.py
hdtools/tests.py
hdtools-0.1.5.dist-info/LICENSE
hdtools-0.1.5.dist-info/METADATA
hdtools-0.1.5.dist-info/WHEEL
hdtools-0.1.5.dist-info/top_level.txt
hdtools-0.1.5.dist-info/RECORD
