Metadata-Version: 2.1
Name: hdtools
Version: 0.1.5
Summary: hd-tools for bitcoin and bitcoin-test
Home-page: https://github.com/morvaridio/hdtools
Author: Mahdi Fooladgar
Author-email: fooladgar@morvarid.io
License: MIT
Keywords: bip32,hd-wallet,bitcoin,bip49,bip44
Platform: UNKNOWN
Classifier: Development Status :: 3 - Alpha
Classifier: Intended Audience :: Developers
Classifier: Topic :: Security :: Cryptography
Classifier: License :: OSI Approved :: MIT License
Classifier: Programming Language :: Python :: 3
Classifier: Programming Language :: Python :: 3.4
Classifier: Programming Language :: Python :: 3.5
Classifier: Programming Language :: Python :: 3.6
Requires-Dist: ecdsa
Requires-Dist: base58
Requires-Dist: mnemonic
